{
	"circles": [
		{
			"type": "orange",
			"radius": 13.053,
			"distance": 33.135,
			"angle": 2.1739821162841368
		},
		{
			"type": "orange",
			"radius": 13.053,
			"distance": 33.135,
			"angle": -2.1739821162841368
		},
		{
			"type": "orange",
			"radius": 9.203,
			"distance": 20.571,
			"angle": 0.0
		},
		{
			"type": "orange",
			"radius": 9.203,
			"distance": 35.128,
			"angle": 0.0
		},
		{
			"type": "orange",
			"radius": 9.203,
			"distance": 30.625,
			"angle": 0.7728317927830891
		},
		{
			"type": "orange",
			"radius": 9.203,
			"distance": 30.625,
			"angle": -0.7728317927830891
		},
		{
			"type": "orange",
			"radius": 9.203,
			"distance": 44.915,
			"angle": 0.6974335690969341
		},
		{
			"type": "orange",
			"radius": 9.203,
			"distance": 44.915,
			"angle": -0.6974335690969341
		},
		{
			"type": "orange",
			"radius": 9.203,
			"distance": 30.101,
			"angle": 1.410575101461817
		},
		{
			"type": "orange",
			"radius": 9.203,
			"distance": 30.101,
			"angle": -1.410575101461817
		},
		{
			"type": "orange",
			"radius": 9.203,
			"distance": 44.472,
			"angle": 1.3414600630828418
		},
		{
			"type": "orange",
			"radius": 9.203,
			"distance": 44.472,
			"angle": -1.3414600630828418
		},
		{
			"type": "thick_blue",
			"radius": 31.94,
			"distance": 3.609,
			"angle": 3.141592653589793
		}
	],
	"size": 28.391,
	"emitter offset": 39.218,
	"bullet type": "regular bullet"
}