{
	"circles": [
		{
			"type": "blue",
			"radius": 18.24,
			"distance": 189.649,
			"angle": 0.07539822368615504
		},
		{
			"type": "blue",
			"radius": 32.4,
			"distance": 224.4,
			"angle": 0.0
		},
		{
			"type": "thick_blue",
			"radius": 54.72,
			"distance": 132.0,
			"angle": 0.0
		},
		{
			"type": "blue",
			"radius": 32.4,
			"distance": 86.632,
			"angle": 0.3518583772020568
		},
		{
			"type": "thick_blue",
			"radius": 38.64,
			"distance": 33.12,
			"angle": 0.0
		},
		{
			"type": "blue",
			"radius": 18.24,
			"distance": 189.649,
			"angle": 2.1697933260793507
		},
		{
			"type": "blue",
			"radius": 32.4,
			"distance": 224.4,
			"angle": 2.0943951023931954
		},
		{
			"type": "thick_blue",
			"radius": 54.72,
			"distance": 132.0,
			"angle": 2.0943951023931954
		},
		{
			"type": "blue",
			"radius": 32.4,
			"distance": 86.632,
			"angle": 2.446253479595252
		},
		{
			"type": "thick_blue",
			"radius": 38.64,
			"distance": 33.12,
			"angle": 2.0943951023931954
		},
		{
			"type": "blue",
			"radius": 18.24,
			"distance": 189.649,
			"angle": -2.01899687870704
		},
		{
			"type": "blue",
			"radius": 32.4,
			"distance": 224.4,
			"angle": -2.0943951023931954
		},
		{
			"type": "thick_blue",
			"radius": 54.72,
			"distance": 132.0,
			"angle": -2.0943951023931954
		},
		{
			"type": "blue",
			"radius": 32.4,
			"distance": 86.632,
			"angle": -1.7425367251911386
		},
		{
			"type": "thick_blue",
			"radius": 38.64,
			"distance": 33.12,
			"angle": -2.0943951023931954
		},
		{
			"type": "thick_blue",
			"radius": 38.64,
			"distance": 0,
			"angle": 0.0
		},
		{
			"type": "blue",
			"radius": 18.24,
			"distance": 189.649,
			"angle": -0.07539822368615504
		},
		{
			"type": "blue",
			"radius": 32.4,
			"distance": 86.632,
			"angle": -0.3518583772020568
		},
		{
			"type": "blue",
			"radius": 18.24,
			"distance": 189.649,
			"angle": 2.01899687870704
		},
		{
			"type": "blue",
			"radius": 32.4,
			"distance": 86.632,
			"angle": 1.7425367251911386
		},
		{
			"type": "blue",
			"radius": 18.24,
			"distance": 189.649,
			"angle": -2.1697933260793507
		},
		{
			"type": "blue",
			"radius": 32.4,
			"distance": 86.632,
			"angle": -2.446253479595252
		},
		{
			"type": "blue",
			"radius": 20.16,
			"distance": 119.04,
			"angle": 2.0943951023931954
		},
		{
			"type": "blue",
			"radius": 20.16,
			"distance": 119.04,
			"angle": -2.0943951023931954
		},
		{
			"type": "blue",
			"radius": 20.16,
			"distance": 119.04,
			"angle": 0.0
		},
		{
			"type": "blue",
			"radius": 20.16,
			"distance": 147.267,
			"angle": 0.34243359924128749
		},
		{
			"type": "blue",
			"radius": 20.16,
			"distance": 147.267,
			"angle": -0.34243359924128749
		},
		{
			"type": "blue",
			"radius": 20.16,
			"distance": 147.267,
			"angle": 2.4368287016344829
		},
		{
			"type": "blue",
			"radius": 20.16,
			"distance": 147.267,
			"angle": 1.7519615031519079
		},
		{
			"type": "blue",
			"radius": 20.16,
			"distance": 147.267,
			"angle": -1.7519615031519079
		},
		{
			"type": "blue",
			"radius": 20.16,
			"distance": 147.267,
			"angle": -2.4368287016344829
		}
	],
	"circles states": {
		"0 29": [
			0,
			1,
			2,
			3,
			4,
			5,
			6,
			7,
			8,
			9,
			10,
			11,
			12,
			13,
			14,
			15
		],
		"30 64": [
			0,
			16,
			1,
			2,
			3,
			17,
			4,
			5,
			18,
			6,
			7,
			8,
			19,
			9,
			10,
			20,
			11,
			12,
			13,
			21,
			14,
			15
		],
		"65 79": [
			0,
			16,
			1,
			2,
			3,
			17,
			4,
			5,
			18,
			6,
			7,
			22,
			8,
			19,
			9,
			10,
			20,
			11,
			12,
			13,
			21,
			14,
			15
		],
		"80 94": [
			0,
			16,
			1,
			2,
			3,
			17,
			4,
			5,
			18,
			6,
			7,
			22,
			8,
			19,
			9,
			10,
			20,
			11,
			12,
			23,
			13,
			21,
			14,
			15
		],
		"95 109": [
			0,
			16,
			1,
			2,
			24,
			3,
			17,
			4,
			5,
			18,
			6,
			7,
			22,
			8,
			19,
			9,
			10,
			20,
			11,
			12,
			23,
			13,
			21,
			14,
			15
		],
		"110 125": [
			0,
			16,
			1,
			2,
			25,
			26,
			3,
			17,
			4,
			5,
			18,
			6,
			7,
			27,
			28,
			8,
			19,
			9,
			10,
			20,
			11,
			12,
			29,
			30,
			13,
			21,
			14,
			15
		]
	},
	"guns": [
		{
			"name": "seeker_spawner_2",
			"scale": 1,
			"distance": 242.84,
			"angle": 0.08482300164692441,
			"rotation type": 0,
			"rotation angle": 1.5707963267948966,
			"shooting type": "spawn orbital seeker",
			"cooldown min": 1200,
			"cooldown max": 1200,
			"delay": 2000,
			"bullet name": "enemy orbital seeker",
			"bullet velocity": 0.42,
			"bullet damage": -5
		},
		{
			"name": "seeker_spawner_2",
			"scale": 1,
			"distance": 242.84,
			"angle": -0.08482300164692441,
			"rotation type": 0,
			"rotation angle": -1.5707963267948966,
			"shooting type": "spawn orbital seeker",
			"cooldown min": 1600,
			"cooldown max": 1600,
			"delay": 2200,
			"bullet name": "enemy orbital seeker",
			"bullet velocity": 0.42,
			"bullet damage": -5
		},
		{
			"name": "seeker_spawner_2",
			"scale": 1,
			"distance": 242.84,
			"angle": -2.009572100746271,
			"rotation type": 0,
			"rotation angle": -0.5235987755982988,
			"shooting type": "spawn orbital seeker",
			"cooldown min": 1800,
			"cooldown max": 1800,
			"delay": 2400,
			"bullet name": "enemy orbital seeker",
			"bullet velocity": 0.42,
			"bullet damage": -5
		},
		{
			"name": "seeker_spawner_2",
			"scale": 1,
			"distance": 242.84,
			"angle": -2.1792181040401199,
			"rotation type": 0,
			"rotation angle": 2.6179938779914946,
			"shooting type": "spawn orbital seeker",
			"cooldown min": 2000,
			"cooldown max": 2000,
			"delay": 2600,
			"bullet name": "enemy orbital seeker",
			"bullet velocity": 0.42,
			"bullet damage": -5
		},
		{
			"name": "seeker_spawner_2",
			"scale": 1,
			"distance": 242.84,
			"angle": 2.1792181040401199,
			"rotation type": 0,
			"rotation angle": -2.6179938779914946,
			"shooting type": "spawn orbital seeker",
			"cooldown min": 2200,
			"cooldown max": 2200,
			"delay": 2800,
			"bullet name": "enemy orbital seeker",
			"bullet velocity": 0.42,
			"bullet damage": -5
		},
		{
			"name": "seeker_spawner_2",
			"scale": 1,
			"distance": 242.84,
			"angle": 2.009572100746271,
			"rotation type": 0,
			"rotation angle": 0.5235987755982988,
			"shooting type": "spawn orbital seeker",
			"cooldown min": 2400,
			"cooldown max": 2400,
			"delay": 3000,
			"bullet name": "enemy orbital seeker",
			"bullet velocity": 0.42,
			"bullet damage": -5
		}
	],
	"guns states": {
		"0 125": [
			0,
			1,
			2,
			3,
			4,
			5
		]
	},
	"radius": 96,
	"rect size": 520.788,
	"max health": 125,
	"velocity": 0.03,
	"death award": {
		"medium": 15,
		"large": 0,
		"ultra": 0
	},
	"spawners": [
		{
			"distance": 0,
			"angle": 0
		}
	],
	"events": []
}